[
    {
        "aos": "2020-08-11 14:00:38.200445 UTC",
        "duration": 921.064731,
        "frequency": 137100000,
        "los": "2020-08-11 14:15:59.265176 UTC",
        "max_elevation": 37.3,
        "satellite": "NOAA 19",
        "status": "PASSED",
        "tca": "2020-08-11 14:08:21.016442 UTC",
        "type": "NOAA"
    },
    {
        "aos": "2020-08-11 15:21:15.590168 UTC",
        "duration": 828.424274,
        "frequency": 137100000,
        "los": "2020-08-11 15:35:04.014442 UTC",
        "max_elevation": 20.8,
        "satellite": "METEOR-M 2",
        "status": "PASSED",
        "tca": "2020-08-11 15:28:10.811347 UTC",
        "type": "METEOR"
    },
    {
        "aos": "2020-08-11 15:41:24.003062 UTC",
        "duration": 914.975045,
        "frequency": 137100000,
        "los": "2020-08-11 15:56:38.978107 UTC",
        "max_elevation": 40.4,
        "satellite": "NOAA 19",
        "status": "CURRENT",
        "tca": "2020-08-11 15:49:02.251795 UTC",
        "type": "NOAA"
    },
    {
        "aos": "2020-08-11 16:12:40.411491 UTC",
        "duration": 907.269397,
        "frequency": 137620000,
        "los": "2020-08-11 16:27:47.680888 UTC",
        "max_elevation": 75.3,
        "satellite": "NOAA 15",
        "status": "INCOMING",
        "tca": "2020-08-11 16:20:14.800153 UTC",
        "type": "NOAA"
    },
    {
        "aos": "2020-08-11 17:01:11.071196 UTC",
        "duration": 918.229096,
        "frequency": 137100000,
        "los": "2020-08-11 17:16:29.300292 UTC",
        "max_elevation": 67.0,
        "satellite": "METEOR-M 2",
        "status": "INCOMING",
        "tca": "2020-08-11 17:08:50.690264 UTC",
        "type": "METEOR"
    },
    {
        "aos": "2020-08-11 18:54:21.993018 UTC",
        "duration": 912.875761,
        "frequency": 137912500,
        "los": "2020-08-11 19:09:34.868779 UTC",
        "max_elevation": 44.6,
        "satellite": "NOAA 18",
        "status": "INCOMING",
        "tca": "2020-08-11 19:01:57.669746 UTC",
        "type": "NOAA"
    },
    {
        "aos": "2020-08-11 23:52:29.745876 UTC",
        "duration": 829.211993,
        "frequency": 137100000,
        "los": "2020-08-12 00:06:18.957869 UTC",
        "max_elevation": 21.0,
        "satellite": "NOAA 19",
        "status": "INCOMING",
        "tca": "2020-08-11 23:59:22.321977 UTC",
        "type": "NOAA"
    },
    {
        "aos": "2020-08-12 01:31:33.695539 UTC",
        "duration": 951.005676,
        "frequency": 137100000,
        "los": "2020-08-12 01:47:24.701215 UTC",
        "max_elevation": 80.7,
        "satellite": "NOAA 19",
        "status": "INCOMING",
        "tca": "2020-08-12 01:39:25.138587 UTC",
        "type": "NOAA"
    },
    {
        "aos": "2020-08-12 01:57:46.718135 UTC",
        "duration": 883.142566,
        "frequency": 137620000,
        "los": "2020-08-12 02:12:29.860701 UTC",
        "max_elevation": 43.7,
        "satellite": "NOAA 15",
        "status": "INCOMING",
        "tca": "2020-08-12 02:05:07.032812 UTC",
        "type": "NOAA"
    },
    {
        "aos": "2020-08-12 02:48:18.163312 UTC",
        "duration": 906.120581,
        "frequency": 137100000,
        "los": "2020-08-12 03:03:24.283893 UTC",
        "max_elevation": 50.0,
        "satellite": "METEOR-M 2",
        "status": "INCOMING",
        "tca": "2020-08-12 02:55:49.710037 UTC",
        "type": "METEOR"
    },
    {
        "aos": "2020-08-12 03:37:49.960221 UTC",
        "duration": 868.063297,
        "frequency": 137620000,
        "los": "2020-08-12 03:52:18.023518 UTC",
        "max_elevation": 31.3,
        "satellite": "NOAA 15",
        "status": "INCOMING",
        "tca": "2020-08-12 03:45:01.729979 UTC",
        "type": "NOAA"
    },
    {
        "aos": "2020-08-12 04:29:01.789043 UTC",
        "duration": 869.795035,
        "frequency": 137100000,
        "los": "2020-08-12 04:43:31.584078 UTC",
        "max_elevation": 28.1,
        "satellite": "METEOR-M 2",
        "status": "INCOMING",
        "tca": "2020-08-12 04:36:14.163952 UTC",
        "type": "METEOR"
    },
    {
        "aos": "2020-08-12 04:44:33.471463 UTC",
        "duration": 939.76982,
        "frequency": 137912500,
        "los": "2020-08-12 05:00:13.241283 UTC",
        "max_elevation": 88.2,
        "satellite": "NOAA 18",
        "status": "INCOMING",
        "tca": "2020-08-12 04:52:20.819197 UTC",
        "type": "NOAA"
    }
]